snips_skill_usb_power-0.0.2.dist-info/DESCRIPTION.rst
snips_skill_usb_power-0.0.2.dist-info/METADATA
snips_skill_usb_power-0.0.2.dist-info/RECORD
snips_skill_usb_power-0.0.2.dist-info/WHEEL
snips_skill_usb_power-0.0.2.dist-info/metadata.json
snips_skill_usb_power-0.0.2.dist-info/top_level.txt
usbpowerskill/__init__.py
usbpowerskill/usbpowerskill.py
