Metadata-Version: 2.0
Name: snips-skill-usb-power
Version: 0.0.2
Summary: turn on/off power to usb ports
Home-page: UNKNOWN
Author: steve ryan
Author-email: stever@syntithenai.com
License: MIT
Keywords: snips
Platform: UNKNOWN
